MobileHelperContent/content.py
pih_MIO_Content-1.47203.dist-info/METADATA
pih_MIO_Content-1.47203.dist-info/WHEEL
pih_MIO_Content-1.47203.dist-info/top_level.txt
pih_MIO_Content-1.47203.dist-info/RECORD
