Metadata-Version: 2.1
Name: pih-MIO-Content
Version: 1.47203
Summary: PIH MIO library
Home-page: https://pacifichosp.com/
Author: Nikita Karachentsev
Author-email: it@pacifichosp.com
License: MIT
Platform: UNKNOWN
Requires-Dist: pih
